enumeration.py
python_enumeration-0.1.dist-info/DESCRIPTION.rst
python_enumeration-0.1.dist-info/METADATA
python_enumeration-0.1.dist-info/RECORD
python_enumeration-0.1.dist-info/WHEEL
python_enumeration-0.1.dist-info/metadata.json
python_enumeration-0.1.dist-info/top_level.txt
