Metadata-Version: 2.0
Name: python-enumeration
Version: 0.1
Summary: An enumeration data type for Python
Home-page: UNKNOWN
Author: UNKNOWN
Author-email: UNKNOWN
License: UNKNOWN
Platform: UNKNOWN
